announce_server/__init__.py
announce_server/__main__.py
announce_server/decorator.py
announce_server/get_ip.py
announce_server/server.py
announce_server-0.0.2.dist-info/METADATA
announce_server-0.0.2.dist-info/WHEEL
announce_server-0.0.2.dist-info/entry_points.txt
announce_server-0.0.2.dist-info/top_level.txt
announce_server-0.0.2.dist-info/RECORD
