Metadata-Version: 2.1
Name: announce-server
Version: 0.0.2
Summary: Announces a server to a host
Home-page: https://git.mlden.com/mm/announce-server.git
Author: Mathematical Michael
Author-email: mm@clfx.cc
License: MIT
Classifier: Development Status :: 3 - Alpha
Classifier: Intended Audience :: Developers
Classifier: License :: OSI Approved :: MIT License
Classifier: Programming Language :: Python :: 3
Classifier: Programming Language :: Python :: 3.7
Classifier: Programming Language :: Python :: 3.8
Classifier: Programming Language :: Python :: 3.9
Classifier: Programming Language :: Python :: 3.10
Requires-Python: >=3.7
Requires-Dist: python-socketio[asyncio_client] (~=5.0.0)
Provides-Extra: api
Requires-Dist: aiohttp ; extra == 'api'
Provides-Extra: dev
Requires-Dist: pytest ; extra == 'dev'
Requires-Dist: pytest-mock ; extra == 'dev'
Requires-Dist: pytest-asyncio ; extra == 'dev'
Requires-Dist: pytest-cov ; extra == 'dev'
Provides-Extra: pub
Requires-Dist: build ; extra == 'pub'
Requires-Dist: wheel ; extra == 'pub'
Requires-Dist: setuptools-scm ; extra == 'pub'
Requires-Dist: twine ; extra == 'pub'
